magenta/__init__.py
magenta/version.py
magenta/common/__init__.py
magenta/common/beam_search.py
magenta/common/beam_search_test.py
magenta/common/concurrency.py
magenta/common/concurrency_test.py
magenta/common/nade.py
magenta/common/nade_test.py
magenta/common/sequence_example_lib.py
magenta/common/state_util.py
magenta/common/state_util_test.py
magenta/common/testing_lib.py
magenta/common/tf_utils.py
magenta/interfaces/__init__.py
magenta/interfaces/midi/__init__.py
magenta/interfaces/midi/magenta_midi.py
magenta/interfaces/midi/midi_clock.py
magenta/interfaces/midi/midi_hub.py
magenta/interfaces/midi/midi_hub_test.py
magenta/interfaces/midi/midi_interaction.py
magenta/models/__init__.py
magenta/models/arbitrary_image_stylization/__init__.py
magenta/models/arbitrary_image_stylization/arbitrary_image_stylization_build_mobilenet_model.py
magenta/models/arbitrary_image_stylization/arbitrary_image_stylization_build_model.py
magenta/models/arbitrary_image_stylization/arbitrary_image_stylization_convert_tflite.py
magenta/models/arbitrary_image_stylization/arbitrary_image_stylization_distill_mobilenet.py
magenta/models/arbitrary_image_stylization/arbitrary_image_stylization_evaluate.py
magenta/models/arbitrary_image_stylization/arbitrary_image_stylization_losses.py
magenta/models/arbitrary_image_stylization/arbitrary_image_stylization_train.py
magenta/models/arbitrary_image_stylization/arbitrary_image_stylization_train_mobile.py
magenta/models/arbitrary_image_stylization/arbitrary_image_stylization_with_weights.py
magenta/models/arbitrary_image_stylization/export_hub.py
magenta/models/arbitrary_image_stylization/nza_model.py
magenta/models/coconet/__init__.py
magenta/models/coconet/coconet_evaluate.py
magenta/models/coconet/coconet_sample.py
magenta/models/coconet/coconet_train.py
magenta/models/coconet/export_saved_model.py
magenta/models/coconet/export_saved_model_test.py
magenta/models/coconet/lib_data.py
magenta_gpu-1.1.7.dist-info/METADATA
magenta_gpu-1.1.7.dist-info/RECORD
magenta_gpu-1.1.7.dist-info/WHEEL
magenta_gpu-1.1.7.dist-info/entry_points.txt
magenta_gpu-1.1.7.dist-info/top_level.txt
